{
  "data": {
    "stage": {
      "shape": [
        {
          "name": "Lamp",
          "text": "toDo",
          "x": "213",
          "y": "16",
          "level": "5",
          "Enabled": "true",
          "Activate": "k",
          "Angle": "0"
        },
        {
          "name": "SquareBox1",
          "text": "toDo",
          "x": "506.75",
          "y": "340.15",
          "level": "5",
          "alpha": "0.6015625",
          "Angle": "0"
        },
        {
          "name": "SquareBox1",
          "text": "toDo",
          "x": "38.1",
          "y": "337.65",
          "level": "5",
          "alpha": "1",
          "Angle": "0"
        },
        {
          "name": "TruckLoader",
          "text": "toDo",
          "x": "198.75",
          "y": "313.5",
          "level": "5",
          "truckPoints": "-37,26:-40.5,-10:-11,-24:11,-24:40.5,-10:37,26:198.75,313.5:175.25,336.5:222.25,336.5:199.3,283.6:198.75,299.25:199.15,301.3:199.3,248.4:198.7,265.2:198.85,213.2:199,225.3:"
        },
        {
          "name": "VerticalBox2",
          "text": "toDo",
          "x": "62",
          "y": "296.25",
          "level": "5",
          "alpha": "1",
          "Angle": "0"
        },
        {
          "name": "SquareBox1",
          "text": "toDo",
          "x": "81.95",
          "y": "336.9",
          "level": "5",
          "alpha": "1",
          "Angle": "0"
        },
        {
          "name": "VerticalBox2",
          "text": "toDo",
          "x": "406.8",
          "y": "341.1",
          "level": "5",
          "alpha": "0.6015625",
          "Angle": "0"
        },
        {
          "name": "VerticalBox2",
          "text": "toDo",
          "x": "59.6",
          "y": "253.3",
          "level": "5",
          "alpha": "1",
          "Angle": "0"
        },
        {
          "name": "VerticalBox2",
          "text": "toDo",
          "x": "466.75",
          "y": "321.15",
          "level": "5",
          "alpha": "0.6015625",
          "Angle": "90"
        },
        {
          "name": "SquareBox1",
          "text": "toDo",
          "x": "506.75",
          "y": "299.95",
          "level": "5",
          "alpha": "0.6015625",
          "Angle": "0"
        },
        {
          "name": "LeaveTheTruck",
          "text": "toDo",
          "x": "291.9",
          "y": "399.85",
          "level": "5",
          "Angle": "\"0\""
        },


        {
          "name": "Truck",
          "text": "toDo",
          "x": "494.8",
          "y": "347.7",
          "level": "5",
          "truckPoints": "-135,50:-135,12:36,12:140,12:140,50:36,12:36,-66:117,-66:140,-20:140,12:564.8,403.7:416.8,403.7:"
        },
        {
          "name": "Shape",
          "text": "toDo",
          "x": "-101",
          "y": "-42",
          "Angle": "\"0\"",
          "level": "5"
        },
        {
          "name": "StaticText",
          "text": "LEVEL 5\nBoom!",
          "x": "140",
          "y": "120",
          "level": "5",
          "Angle": "0"
        },
        {
          "name": "verts",
          "xy1": "196.2738653582383,-320.33329461447045 : 157.2894903582383,-320.33329461447045 : 157.2894903582383,-340.33329461447045 : 160.4535528582383,-345.05985711447045 : 195.4535528582383,-345.05985711447045 :",
          "xy2": "613.5703125,-2.75 : 574.5859375,-2.75 : 574.5859375,-22.75 : 577.75,-27.4765625 : 612.75,-27.4765625 :"
        },
        {
          "name": "verts",
          "xy1": "196.2738653582383,-320.33329461447045 : 200.4535528582383,-318.10673211447045 : 155.4535528582383,-318.10673211447045 : 157.2894903582383,-320.33329461447045 :",
          "xy2": "613.5703125,-2.75 : 617.75,-0.5234375 : 572.75,-0.5234375 : 574.5859375,-2.75 :"
        },
        {
          "name": "verts",
          "xy1": "157.2894903582383,-285.33329461447045 : 196.2738653582383,-285.33329461447045 : 195.4535528582383,-50.99735711447045 : 160.4535528582383,-50.99735711447045 : 157.2894903582383,-55.33329461447045 :",
          "xy2": "574.5859375,32.25 : 613.5703125,32.25 : 612.75,266.5859375 : 577.75,266.5859375 : 574.5859375,262.25 :"
        },
        {
          "name": "verts",
          "xy1": "157.2894903582383,-285.33329461447045 : 155.4535528582383,-287.01298211447045 : 200.4535528582383,-287.01298211447045 : 196.2738653582383,-285.33329461447045 :",
          "xy2": "574.5859375,32.25 : 572.75,30.5703125 : 617.75,30.5703125 : 613.5703125,32.25 :"
        },
        {
          "name": "verts",
          "xy1": "-37.710509641761746,-285.33329461447045 : -59.546447141761746,-287.01298211447045 : -34.546447141761746,-287.01298211447045 :",
          "xy2": "379.5859375,32.25 : 357.75,30.5703125 : 382.75,30.5703125 :"
        },
        {
          "name": "verts",
          "xy1": "-58.726134641761746,-125.33329461447045 : -59.546447141761746,-287.01298211447045 : -37.710509641761746,-285.33329461447045 : -37.710509641761746,-125.33329461447045 : -39.546447141761746,-122.09110711447045 : -54.546447141761746,-122.09110711447045 :",
          "xy2": "358.5703125,192.25 : 357.75,30.5703125 : 379.5859375,32.25 : 379.5859375,192.25 : 377.75,195.4921875 : 362.75,195.4921875 :"
        },
        {
          "name": "verts",
          "xy1": "280.4535528582383,-287.01298211447045 : -394.54644714176175,-287.01298211447045 : 284.2426153582383,-290.33329461447045 :",
          "xy2": "697.75,30.5703125 : 22.75,30.5703125 : 701.5390625,27.25 :"
        },
        {
          "name": "verts",
          "xy1": "760.4535528582383,155.87764288552955 : 540.4535528582383,155.87764288552955 : 765.3363653582383,154.66670538552955 :",
          "xy2": "1177.75,473.4609375 : 957.75,473.4609375 : 1182.6328125,472.25 :"
        },
        {
          "name": "verts",
          "xy1": "535.4535528582383,162.98701788552955 : -64.54644714176175,162.98701788552955 : 540.2582403582383,159.66670538552955 :",
          "xy2": "952.75,480.5703125 : 352.75,480.5703125 : 957.5546875,477.25 :"
        },
        {
          "name": "verts",
          "xy1": "-417.78863464176175,174.66670538552955 : -396.69488464176175,169.66670538552955 : -396.69488464176175,174.66670538552955 : -399.54644714176175,177.92061163552955 : -414.54644714176175,177.92061163552955 :",
          "xy2": "-0.4921875,492.25 : 20.6015625,487.25 : 20.6015625,492.25 : 17.75,495.50390625 : 2.75,495.50390625 :"
        },
        {
          "name": "verts",
          "xy1": "-417.78863464176175,174.66670538552955 : -418.72613464176175,164.66670538552955 : -394.54644714176175,165.87764288552955 : -396.69488464176175,169.66670538552955 :",
          "xy2": "-0.4921875,492.25 : -1.4296875,482.25 : 22.75,483.4609375 : 20.6015625,487.25 :"
        },
        {
          "name": "verts",
          "xy1": "-66.69488464176175,109.66670538552955 : -394.54644714176175,40.95576788552955 : -69.54644714176175,40.95576788552955 : -66.69488464176175,44.66670538552955 :",
          "xy2": "350.6015625,427.25 : 22.75,358.5390625 : 347.75,358.5390625 : 350.6015625,362.25 :"
        },
        {
          "name": "verts",
          "xy1": "540.4535528582383,155.87764288552955 : -64.54644714176175,112.98701788552955 : 760.4535528582383,112.98701788552955 : 765.3363653582383,114.66670538552955 : 765.3363653582383,154.66670538552955 :",
          "xy2": "957.75,473.4609375 : 352.75,430.5703125 : 1177.75,430.5703125 : 1182.6328125,432.25 : 1182.6328125,472.25 :"
        },
        {
          "name": "verts",
          "xy1": "-64.54644714176175,162.98701788552955 : -64.54644714176175,112.98701788552955 : 540.4535528582383,155.87764288552955 : 540.2582403582383,159.66670538552955 :",
          "xy2": "352.75,480.5703125 : 352.75,430.5703125 : 957.75,473.4609375 : 957.5546875,477.25 :"
        },
        {
          "name": "verts",
          "xy1": "-418.72613464176175,164.66670538552955 : -394.54644714176175,40.95576788552955 : -66.69488464176175,109.66670538552955 : -64.54644714176175,112.98701788552955 : -64.54644714176175,162.98701788552955 : -69.54644714176175,165.87764288552955 : -394.54644714176175,165.87764288552955 :",
          "xy2": "-1.4296875,482.25 : 22.75,358.5390625 : 350.6015625,427.25 : 352.75,430.5703125 : 352.75,480.5703125 : 347.75,483.4609375 : 22.75,483.4609375 :"
        },
        {
          "name": "verts",
          "xy1": "-418.72613464176175,164.66670538552955 : -396.69488464176175,39.66670538552955 : -394.54644714176175,40.95576788552955 :",
          "xy2": "-1.4296875,482.25 : 20.6015625,357.25 : 22.75,358.5390625 :"
        },
        {
          "name": "verts",
          "xy1": "-417.78863464176175,-315.33329461447045 : -396.69488464176175,-285.33329461447045 : -396.69488464176175,39.66670538552955 : -418.72613464176175,164.66670538552955 :",
          "xy2": "-0.4921875,2.25 : 20.6015625,32.25 : 20.6015625,357.25 : -1.4296875,482.25 :"
        },
        {
          "name": "verts",
          "xy1": "-417.78863464176175,-315.33329461447045 : -394.54644714176175,-287.01298211447045 : -396.69488464176175,-285.33329461447045 :",
          "xy2": "-0.4921875,2.25 : 22.75,30.5703125 : 20.6015625,32.25 :"
        },
        {
          "name": "verts",
          "xy1": "-417.78863464176175,-315.33329461447045 : -414.54644714176175,-318.10673211447045 : 280.4535528582383,-318.10673211447045 : 284.2426153582383,-315.33329461447045 : 284.2426153582383,-290.33329461447045 : -394.54644714176175,-287.01298211447045 :",
          "xy2": "-0.4921875,2.25 : 2.75,-0.5234375 : 697.75,-0.5234375 : 701.5390625,2.25 : 701.5390625,27.25 : 22.75,30.5703125 :"
        }
      ]
    }
  },
  "#omit-xml-declaration": "yes"
}